{
  "fill-specializations" : [
    {
      "value" : {
        "automatic-gradient" : "extended-srgb:0.00000,0.53333,1.00000,1.00000"
      }
    },
    {
      "appearance" : "dark",
      "value" : {
        "automatic-gradient" : "display-p3:0.38877,0.35087,0.49461,1.00000"
      }
    }
  ],
  "groups" : [
    {
      "layers" : [
        {
          "glass" : false,
          "hidden" : false,
          "image-name" : "Ghost.svg",
          "name" : "Ghost",
          "position" : {
            "scale" : 4.5,
            "translation-in-points" : [
              0,
              0
            ]
          }
        }
      ],
      "shadow" : {
        "kind" : "neutral",
        "opacity" : 0.5
      },
      "translucency" : {
        "enabled" : true,
        "value" : 0.5
      }
    }
  ],
  "supported-platforms" : {
    "circles" : [
      "watchOS"
    ],
    "squares" : "shared"
  }
}